{
  "title": "Rodrigo Santos",
  "description": "Full Stack Web Developer",
  "socials": {
    "twitter": {
      "name": "twitter",
      "link": "http://twitter.com",
      "icon": "twitter"
    },
    "instagram": {
      "name": "instagram",
      "link": "http://instagram.com",
      "icon": "instagram"
    }
  },
  "start": {
    "background": "#cccccc",
    "align": "right"
  },
  "styles": {
    "primary": "#ffffff",
    "secondary": "#000000",
    "accent": "",
    "background": "#000000",
    "text": "#ffffff"
  }
}
